{
  "id": "08cf0388-40cc-4f57-a879-de00c61bab17",
  "type": "missing_building",
  "timestamp": "2025-12-25T07:22:23.907373+00:00",
  "image": "ml/feedback/missing_building/images/08cf0388-40cc-4f57-a879-de00c61bab17.png",
  "geometry": {
    "type": "Polygon",
    "coordinates": [
      [
        [
          73.10238897800447,
          33.61222921083325
        ],
        [
          73.1025566160679,
          33.61224149646838
        ],
        [
          73.1025740504265,
          33.612050510488174
        ],
        [
          73.1024131178856,
          33.61203040667618
        ],
        [
          73.10238897800447,
          33.61222921083325
        ]
      ]
    ]
  },
  "mask": "ml/feedback/missing_building/masks/08cf0388-40cc-4f57-a879-de00c61bab17.png"
}