{
  "id": "d4e1c947-7077-461a-80dd-fca9afea41cd",
  "type": "missing_building",
  "timestamp": "2025-12-27T13:10:49.631698+00:00",
  "image": "ml/feedback/missing_building/images/d4e1c947-7077-461a-80dd-fca9afea41cd.png",
  "geometry": {
    "type": "Polygon",
    "coordinates": [
      [
        [
          73.0900038778782,
          33.611579186550884
        ],
        [
          73.09000521898271,
          33.611480900665754
        ],
        [
          73.09008166193964,
          33.61147531623708
        ],
        [
          73.09008300304414,
          33.611518874771
        ],
        [
          73.09012725949289,
          33.611521108541396
        ],
        [
          73.09013262391092,
          33.611478666894314
        ],
        [
          73.09022650122644,
          33.611477550008594
        ],
        [
          73.09022784233095,
          33.61156690082136
        ],
        [
          73.0900038778782,
          33.611579186550884
        ]
      ]
    ]
  },
  "mask": "ml/feedback/missing_building/masks/d4e1c947-7077-461a-80dd-fca9afea41cd.png"
}