{
  "id": "fc54160c-bfdf-4aa6-81d0-3ab6ffd8bc3c",
  "type": "missing_building",
  "timestamp": "2025-12-27T13:09:34.016965+00:00",
  "image": "ml/feedback/missing_building/images/fc54160c-bfdf-4aa6-81d0-3ab6ffd8bc3c.png",
  "geometry": {
    "type": "Polygon",
    "coordinates": [
      [
        [
          73.08948889374734,
          33.61188856298045
        ],
        [
          73.08953315019609,
          33.61188521233912
        ],
        [
          73.0895371735096,
          33.611905316184995
        ],
        [
          73.08958411216737,
          33.61190196554435
        ],
        [
          73.08958545327187,
          33.61188297857819
        ],
        [
          73.08975175023079,
          33.61188186169771
        ],
        [
          73.08976113796236,
          33.61189526426265
        ],
        [
          73.08981344103813,
          33.611891913621605
        ],
        [
          73.08981612324716,
          33.61187180977262
        ],
        [
          73.08985099196434,
          33.61186957601131
        ],
        [
          73.08984830975534,
          33.6117768748668
        ],
        [
          73.0894982814789,
          33.61178580992121
        ],
        [
          73.08949157595634,
          33.61179027744808
        ],
        [
          73.08948889374734,
          33.61188856298045
        ]
      ]
    ]
  },
  "mask": "ml/feedback/missing_building/masks/fc54160c-bfdf-4aa6-81d0-3ab6ffd8bc3c.png"
}